atcoder/__init__.py
atcoder/__main__.py
atcoder/auth.py
atcoder/constant.py
atcoder/contest.py
atcoder/crawl.py
atcoder/editorial.py
atcoder/home.py
atcoder/language.py
atcoder/login.py
atcoder/network.py
atcoder/score.py
atcoder/scrape.py
atcoder/standings.py
atcoder/submission.py
atcoder/submit.py
atcoder/task.py
atcoder/top.py
atcoder/user.py
atcoder/user_agent.py
atcoder/utils.py
src/languages.yaml
atcoder_api-0.3.4.dist-info/LICENSE
atcoder_api-0.3.4.dist-info/WHEEL
atcoder_api-0.3.4.dist-info/METADATA
atcoder_api-0.3.4.dist-info/RECORD
