Metadata-Version: 2.1
Name: atcoder-api
Version: 0.3.4
Summary: AtCoder API.
Home-page: https://atcoder-api-python.readthedocs.io
License: MIT
Keywords: atcoder,api
Author: Hiroshi Tsuyuki
Author-email: kagemeka1@gmail.com
Maintainer: Hiroshi Tsuyuki
Maintainer-email: kagemeka1@gmail.com
Requires-Python: >=3.8,<3.11
Classifier: License :: OSI Approved :: MIT License
Classifier: Programming Language :: Python :: 3
Classifier: Programming Language :: Python :: 3.10
Classifier: Programming Language :: Python :: 3.8
Classifier: Programming Language :: Python :: 3.9
Requires-Dist: PyYAML
Requires-Dist: aiodns
Requires-Dist: aiohttp
Requires-Dist: beautifulsoup4
Requires-Dist: boto3
Requires-Dist: cchardet
Requires-Dist: lxml
Requires-Dist: pandas
Requires-Dist: requests
Requires-Dist: selenium
Requires-Dist: tqdm
Project-URL: Documentation, https://atcoder-api-python.readthedocs.io
Project-URL: Repository, https://github.com/competitive-programming-helper/atcoder-api
